pl_minio_callback/__init__.py
pl_minio_callback/minio_callback.py
pl_minio_callback/minio_util.py
pl_minio_callback-1.0.4.dist-info/LICENSE
pl_minio_callback-1.0.4.dist-info/METADATA
pl_minio_callback-1.0.4.dist-info/WHEEL
pl_minio_callback-1.0.4.dist-info/top_level.txt
pl_minio_callback-1.0.4.dist-info/RECORD
