Metadata-Version: 2.1
Name: pl-minio-callback
Version: 1.0.4
Summary: Callback prepared to log checkpoints to minio server.
Home-page: https://github.com/dpulpeiro/pl-minio-callback
Author: Daniel Garcia Pulpeiro
Author-email: danielgarciapulpeiro@gmail.com
License: UNKNOWN
Project-URL: Bug Tracker, https://github.com/dpulpeiro/pl-minio-callback/issues
Platform: UNKNOWN
Classifier: Programming Language :: Python :: 3
Classifier: License :: OSI Approved :: MIT License
Classifier: Operating System :: OS Independent
Classifier: Topic :: Scientific/Engineering :: Artificial Intelligence
Classifier: Topic :: System :: Logging
Requires-Python: >=3.6
License-File: LICENSE
Requires-Dist: pytorch-lightning
Requires-Dist: minio
